{
  "required": true,
  "minVersion": "0.8",
  "package": "com.itlesports.nightmaremode.mixin",
  "compatibilityLevel": "JAVA_17",
  "mixins": [
    "ArmorItemSpecialMixin",
    "BiomeEndDecoratorMixin",
    "BiomeGenBaseAccessor",
    "BiomeGenBaseMixin",
    "BiomeGenEndMixin",
    "BiomeGenHellMixin",
    "BiomeGenJungleMixin",
    "BlockLogMixin",
    "BonusBasketGeneratorMixin",
    "BTWEntityMapperMixin",
    "BTWItemsMixin",
    "BTWSquidEntityMixin",
    "BucketItemWaterMixin",
    "CauldronRecipeListMixin",
    "CraftingRecipeListMixin",
    "CrucibleRecipeListMixin",
    "DireWolfEntityMixin",
    "EmeraldPileItemMixin",
    "EnchantmentDurabilityMixin",
    "EnchantmentHelperMixin",
    "EnchantmentProtectionMixin",
    "EntityAccessor",
    "EntityAIAttackOnCollideMixin",
    "EntityAICreeperSwellMixin",
    "EntityAINearestAttackableTargetMixin",
    "EntityAnimalInvoker",
    "EntityAnimalMixin",
    "EntityArrowMixin",
    "EntityBatMixin",
    "EntityBlazeMixin",
    "EntityChickenMixin",
    "EntityCowMixin",
    "EntityCreeperAccessor",
    "EntityCreeperMixin",
    "EntityDragonMixin",
    "EntityEnderCrystalMixin",
    "EntityEndermanMixin",
    "EntityEnderPearlMixin",
    "EntityFireballMixin",
    "EntityFishHookAccessor",
    "EntityFishHookMixin",
    "EntityGhastMixin",
    "EntityHorseMixin",
    "EntityItemMixin",
    "EntityLivingBaseMixin",
    "EntityLivingMixin",
    "EntityMagmaCubeMixin",
    "EntityMixin",
    "EntityMobMixin",
    "EntityPigMixin",
    "EntityPigZombieMixin",
    "EntityPlayerMixin",
    "EntityPlayerMPMixin",
    "EntityPlayerSPMixin",
    "EntitySheepMixin",
    "EntitySilverfishMixin",
    "EntitySkeletonMixin",
    "EntitySlimeMixin",
    "EntitySmallFireballMixin",
    "EntitySnowballMixin",
    "EntitySpiderMixin",
    "EntityThrowableMixin",
    "EntityVillagerMixin",
    "EntityWitchMixin",
    "EntityWitherMixin",
    "EntityWitherSkullMixin",
    "EntityZombieMixin",
    "FoodItemMixin",
    "FoodStatsMixin",
    "HardcoreSpawnUtilsMixin",
    "HostileDifficultyMixin",
    "InventoryPlayerMixin",
    "ItemAppleGoldMixin",
    "ItemBowMixin",
    "ItemEnderEyeMixin",
    "ItemFoodMixin",
    "ItemInvoker",
    "ItemPotionMixin",
    "JungleSpiderEntityMixin",
    "LibrarianVillagerEntityMixin",
    "MillstoneRecipeListMixin",
    "MinecraftServerMixin",
    "MyceliumBlockMixin",
    "PotionMixin",
    "SkeletonArrowAttackBehaviorMixin",
    "SmeltingRecipeListMixin",
    "SoulforgeRecipeListMixin",
    "SpawnerAnimalsMixin",
    "SpiderWebEntityMixin",
    "StructureStrongholdStonesMixin",
    "TradeListMixin",
    "UrnEntityMixin",
    "WickerWeavingItemMixin",
    "WolfHowlBehaviorMixin",
    "WorldInfoAccessor",
    "WorldInfoMixin",
    "WorldMixin",
    "WorldProviderHellMixin",
    "ZombieBreakBarricadeBehaviorHostileMixin",
    "ZombieBreakBarricadeBehaviorMixin",
    "blocks.AestheticOpaqueEarthBlockMixin",
    "blocks.AnvilBlockMixin",
    "blocks.BedBlockBaseMixin",
    "blocks.BlockClayMixin",
    "blocks.BlockFluidMixin",
    "blocks.BlockGrassMixin",
    "blocks.BlockLeavesMixin",
    "blocks.BlockMixin",
    "blocks.BlockMushroomMixin",
    "blocks.BlockPortalMixin",
    "blocks.BlockTallGrassMixin",
    "blocks.BlockVineMixin",
    "blocks.CampfireTileEntityMixin",
    "blocks.CobblestoneBlockMixin",
    "blocks.CobblestoneStairsBlockMixin",
    "blocks.HopperTileEntityMixin",
    "blocks.KilnBlockMixin",
    "blocks.MillstoneTileEntityMixin",
    "blocks.MushroomBlockBrownMixin",
    "blocks.OreBlockAccessor",
    "blocks.OreBlockMixin",
    "blocks.OvenTileEntityMixin",
    "blocks.PotatoBlockMixin",
    "blocks.SawBlockMixin",
    "blocks.UnfiredBrickTileEntityMixin",
    "component.ComponentMineshaftCorridorMixin",
    "component.ComponentScatteredFeatureDesertPyramidMixin",
    "component.ComponentStrongholdChestCorridorMixin",
    "component.ComponentStrongholdCorridorMixin",
    "component.ComponentStrongholdCrossingMixin",
    "component.ComponentStrongholdMixin",
    "component.ComponentStrongholdPortalRoomMixin",
    "component.ComponentStrongholdRoomCrossingMixin",
    "component.ComponentStrongholdStairsMixin",
    "component.ComponentStrongholdStairsStraightMixin",
    "component.ComponentVillageChurchMixin",
    "gui.ContainerRepairMixin",
    "gui.LoadingScreenRendererMixin"
  ],
  "client": [
    "MinecraftMixin",
    "blocks.MillstoneBlockMixin",
    "gui.GuiContainerMixin",
    "gui.GuiCreateWorldMixin",
    "gui.GuiGameOverMixin",
    "gui.GuiIngameMenuMixin",
    "gui.GuiIngameMixin",
    "gui.GuiMainMenuMixin",
    "gui.GuiOptionsMixin",
    "gui.GuiScreenMixin",
    "gui.GuiShareToLanMixin",
    "gui.GuiSleepMPMixin",
    "gui.GuiSlotMixin",
    "render.BTWRenderMapperMixin",
    "render.CanvasRendererMixin",
    "render.ColorizeWorldMixin",
    "render.EntityRendererMixin",
    "render.ItemRendererMixin",
    "render.RenderBlazeMixin",
    "render.RenderChickenMixin",
    "render.RenderCowMixin",
    "render.RenderCreeperMixin",
    "render.RenderEnderCrystalMixin",
    "render.RenderEndermanMixin",
    "render.RenderGhastMixin",
    "render.RenderGlobalMixin",
    "render.RenderHorseMixin",
    "render.RenderPigMixin",
    "render.RenderPlayerMixin",
    "render.RenderSheepMixin",
    "render.RenderSkeletonMixin",
    "render.RenderSlimeMixin",
    "render.RenderSpiderMixin",
    "render.RenderVillagerMixin",
    "render.RenderWitchMixin",
    "render.RenderWitherMixin",
    "render.RenderZombieMixin",
    "render.SquidRendererMixin"
  ],
  "injectors": {
    "defaultRequire": 1
  }
}